fake_data_for_learning/__init__.py
fake_data_for_learning/contingency_tables.py
fake_data_for_learning/fake_data_for_learning.py
fake_data_for_learning/probability_polytopes.py
fake_data_for_learning/utils.py
fake_data_for_learning-0.4.4.dist-info/LICENSE
fake_data_for_learning-0.4.4.dist-info/METADATA
fake_data_for_learning-0.4.4.dist-info/WHEEL
fake_data_for_learning-0.4.4.dist-info/top_level.txt
fake_data_for_learning-0.4.4.dist-info/RECORD
