Metadata-Version: 2.1
Name: fake-data-for-learning
Version: 0.4.4
Author: Paul Larsen
Author-email: munichpavel@gmail.com
License: MIT license
Project-URL: Homepage, https://munichpavel.github.io/fake-data-for-learning/
Project-URL: Bug Tracker, https://github.com/munichpavel/fake-data-for-learning/issues
Project-URL: Documentation, https://munichpavel.github.io/fake-data-docs/html/index.html
Project-URL: Source Code, https://github.com/munichpavel/fake-data-for-learning/
Classifier: Development Status :: 2 - Pre-Alpha
Classifier: Intended Audience :: Developers
Classifier: License :: OSI Approved :: MIT License
Classifier: Natural Language :: English
Classifier: Programming Language :: Python :: 3.6
Classifier: Programming Language :: Python :: 3.7
Requires-Python: >3.6
License-File: LICENSE
Requires-Dist: networkx (>=2.4)
Requires-Dist: pandas (>=0.25)
Requires-Dist: numpy
Requires-Dist: scikit-learn (>=0.21.3)
Requires-Dist: scipy (>=1.3)
Requires-Dist: xarray
Provides-Extra: probability_polytope
Requires-Dist: pypoman ; extra == 'probability_polytope'
